rekcurd/__init__.py
rekcurd/_project.py
rekcurd/_version.py
rekcurd/console_scripts/__init__.py
rekcurd/console_scripts/errors.py
rekcurd/console_scripts/startapp_handler.py
rekcurd/core/__init__.py
rekcurd/core/rekcurd_dashboard_servicer.py
rekcurd/core/rekcurd_worker.py
rekcurd/core/rekcurd_worker_servicer.py
rekcurd/data_servers/__init__.py
rekcurd/data_servers/aws_s3_handler.py
rekcurd/data_servers/ceph_handler.py
rekcurd/data_servers/data_handler.py
rekcurd/data_servers/gcs_handler.py
rekcurd/data_servers/local_handler.py
rekcurd/logger/__init__.py
rekcurd/logger/logger_fluent.py
rekcurd/logger/logger_interface.py
rekcurd/logger/logger_jsonlogger.py
rekcurd/protobuf/__init__.py
rekcurd/protobuf/rekcurd_pb2.py
rekcurd/protobuf/rekcurd_pb2_grpc.py
rekcurd/template/app.py-tpl
rekcurd/template/requirements.txt-tpl
rekcurd/template/settings.yml-tpl
rekcurd/template/start.sh-tpl
rekcurd/utils/__init__.py
rekcurd/utils/rekcurd_config.py
rekcurd-1.0.1.post1.dist-info/LICENSE
rekcurd-1.0.1.post1.dist-info/METADATA
rekcurd-1.0.1.post1.dist-info/WHEEL
rekcurd-1.0.1.post1.dist-info/entry_points.txt
rekcurd-1.0.1.post1.dist-info/top_level.txt
rekcurd-1.0.1.post1.dist-info/RECORD
